miaolib/__init__.py
miaolib/scheme.py
miaolib/server.py
miaolib/static/.DS_Store
miaolib/static/favicon.ico
miaolib/static/index.html
miaolib/static/css/app.62ed455a.css
miaolib/static/css/app.a4c956ce.css
miaolib/static/css/chunk-vendors.737c788d.css
miaolib/static/css/chunk-vendors.e1ebeda0.css
miaolib/static/js/app.239a7702.js
miaolib/static/js/app.239a7702.js.map
miaolib/static/js/app.323da5a7.js
miaolib/static/js/app.323da5a7.js.map
miaolib/static/js/app.3447875f.js
miaolib/static/js/app.3447875f.js.map
miaolib/static/js/app.495d5b4e.js
miaolib/static/js/app.495d5b4e.js.map
miaolib/static/js/app.536cb5ea.js
miaolib/static/js/app.536cb5ea.js.map
miaolib/static/js/app.553b8734.js
miaolib/static/js/app.553b8734.js.map
miaolib/static/js/app.73738f69.js
miaolib/static/js/app.73738f69.js.map
miaolib/static/js/app.895eac9b.js
miaolib/static/js/app.895eac9b.js.map
miaolib/static/js/app.8fd60588.js
miaolib/static/js/app.8fd60588.js.map
miaolib/static/js/app.9af3b08e.js
miaolib/static/js/app.9af3b08e.js.map
miaolib/static/js/app.cf325132.js
miaolib/static/js/app.cf325132.js.map
miaolib/static/js/app.cf3d2554.js
miaolib/static/js/app.cf3d2554.js.map
miaolib/static/js/app.f6d4e3c1.js
miaolib/static/js/app.f6d4e3c1.js.map
miaolib/static/js/chunk-vendors.9a1536b9.js
miaolib/static/js/chunk-vendors.9a1536b9.js.map
miaolib/static/js/chunk-vendors.e7d8dd65.js
miaolib/static/js/chunk-vendors.e7d8dd65.js.map
MIAOlib-0.1.0.dist-info/METADATA
MIAOlib-0.1.0.dist-info/WHEEL
MIAOlib-0.1.0.dist-info/top_level.txt
MIAOlib-0.1.0.dist-info/RECORD
