Metadata-Version: 2.1
Name: MIAOlib
Version: 0.1.0
Summary: MIAO ("Miao Is A web demO generator") is a non-intrusive web demo generator that quickly converts a function or piece of code into a web UI for temporary demos or tests, out-of-the-box without a complex configuration process.
Home-page: https://github.com/TheColdVoid/MIAO
Author: TheVoid
Author-email: thevoid2333@gmail.com
License: MIT
Platform: UNKNOWN
Classifier: License :: OSI Approved :: MIT License
Classifier: Programming Language :: Python
Classifier: Programming Language :: Python :: 3
Classifier: Programming Language :: Python :: 3.5
Requires-Python: >=3.6.0
Requires-Dist: quart
Requires-Dist: quart-cors
Requires-Dist: uvicorn
